zeusdb/__init__.py
zeusdb/py.typed
zeusdb-0.0.8.dist-info/METADATA
zeusdb-0.0.8.dist-info/WHEEL
zeusdb-0.0.8.dist-info/licenses/LICENSE
zeusdb-0.0.8.dist-info/licenses/NOTICE
zeusdb-0.0.8.dist-info/RECORD
