Metadata-Version: 2.4
Name: zeusdb
Version: 0.0.8
Summary: Ultra-light and blazingly-fast database management system
Project-URL: Repository, https://github.com/zeusdb/zeusdb
Project-URL: Documentation, https://docs.zeusdb.com
Project-URL: Bug Tracker, https://github.com/zeusdb/zeusdb/issues
Author-email: ZeusDB <contact@zeusdb.com>
License:                                  Apache License
License-File: LICENSE
License-File: NOTICE
Keywords: ann,approximate nearest neighbor,approximate nearest neighbor search,cosine similarity,rag,ranking,reranking,retrieval,retrieval-augmented-generation,vector database,vector database management system,vector search,vector similarity,vector store,zeusdb
Classifier: Development Status :: 4 - Beta
Classifier: Intended Audience :: Developers
Classifier: License :: OSI Approved :: Apache Software License
Classifier: Programming Language :: Python :: 3
Classifier: Programming Language :: Python :: 3 :: Only
Classifier: Programming Language :: Python :: 3.10
Classifier: Programming Language :: Python :: 3.11
Classifier: Programming Language :: Python :: 3.12
Classifier: Programming Language :: Python :: 3.13
Classifier: Programming Language :: Python :: Implementation :: CPython
Classifier: Topic :: Database
Classifier: Topic :: Scientific/Engineering
Classifier: Topic :: Scientific/Engineering :: Artificial Intelligence
Requires-Python: >=3.10
Requires-Dist: zeusdb-vector-database>=0.4.1
Provides-Extra: docs
Requires-Dist: linkify-it-py; extra == 'docs'
Requires-Dist: myst-parser; extra == 'docs'
Requires-Dist: pydata-sphinx-theme; extra == 'docs'
Requires-Dist: sphinx; extra == 'docs'
Requires-Dist: sphinx-autobuild; extra == 'docs'
Requires-Dist: sphinx-design; extra == 'docs'
Requires-Dist: sphinx-sitemap; extra == 'docs'
